{"mean":{"confidence_interval":{"confidence_level":0.95,"lower_bound":66118.44718067438,"upper_bound":67624.88493692254},"point_estimate":66855.65328036822,"standard_error":383.5143948265339},"median":{"confidence_interval":{"confidence_level":0.95,"lower_bound":65751.796875,"upper_bound":67781.30889423077},"point_estimate":66894.82769726247,"standard_error":591.7481785117753},"median_abs_dev":{"confidence_interval":{"confidence_level":0.95,"lower_bound":2756.033510386453,"upper_bound":4429.3374617772215},"point_estimate":3402.3884219088372,"standard_error":415.76331275722526},"slope":{"confidence_interval":{"confidence_level":0.95,"lower_bound":65422.76697733993,"upper_bound":68079.3409882574},"point_estimate":66695.60614341657,"standard_error":677.4913816963343},"std_dev":{"confidence_interval":{"confidence_level":0.95,"lower_bound":3218.1773144485956,"upper_bound":4397.81305357601},"point_estimate":3833.1797618733067,"standard_error":300.42636214140185}}